{
    "clash-dashboard": {
        "cargoLocks": null,
        "date": "2023-04-29",
        "extract": null,
        "name": "clash-dashboard",
        "passthru": null,
        "pinned": false,
        "src": {
            "deepClone": false,
            "fetchSubmodules": false,
            "leaveDotGit": false,
            "name": null,
            "rev": "bd9971a0aad807cf121c29bf20c55f7a82d02043",
            "sha256": "sha256-hLDAJLQPtyaoTS+Y0GjzDBqdyF68idOajmQGJXiE/nQ=",
            "type": "git",
            "url": "https://github.com/Dreamacro/clash-dashboard.git"
        },
        "version": "bd9971a0aad807cf121c29bf20c55f7a82d02043"
    },
    "clash-premium-x86_64-linux": {
        "cargoLocks": null,
        "date": null,
        "extract": null,
        "name": "clash-premium-x86_64-linux",
        "passthru": null,
        "pinned": false,
        "src": {
            "name": null,
            "sha256": "sha256-8zvNRWmaHvH+fcpjqM8OxuUFLM9tqjIUeZobmUxqg+4=",
            "type": "url",
            "url": "https://github.com/Dreamacro/clash/releases/download/premium/clash-linux-amd64-2023.04.16.gz"
        },
        "version": "2023.04.16"
    },
    "kmonad-bin": {
        "cargoLocks": null,
        "date": null,
        "extract": null,
        "name": "kmonad-bin",
        "passthru": null,
        "pinned": false,
        "src": {
            "name": null,
            "sha256": "sha256-g55Y58wj1t0GhG80PAyb4PknaYGJ5JfaNe9RlnA/eo8=",
            "type": "url",
            "url": "https://github.com/kmonad/kmonad/releases/download/0.4.1/kmonad-0.4.1-linux"
        },
        "version": "0.4.1"
    },
    "maxmind-geoip": {
        "cargoLocks": null,
        "date": null,
        "extract": null,
        "name": "maxmind-geoip",
        "passthru": null,
        "pinned": false,
        "src": {
            "name": null,
            "sha256": "sha256-QBHvir5e0JDIYkOouFsPC7SwAQ4fxdUxZcGBWLEUejU=",
            "type": "url",
            "url": "https://github.com/Dreamacro/maxmind-geoip/releases/download/20230412/Country.mmdb"
        },
        "version": "20230412"
    },
    "sweet": {
        "cargoLocks": null,
        "date": "2023-04-29",
        "extract": null,
        "name": "sweet",
        "passthru": null,
        "pinned": false,
        "src": {
            "deepClone": false,
            "fetchSubmodules": false,
            "leaveDotGit": false,
            "name": null,
            "rev": "fb691988f68737556f30c54a6df6d440b9053699",
            "sha256": "sha256-v6bVu8ClgUFMWhwfwrcrsaRm7SusMumuiUpQQ+Yqjlw=",
            "type": "git",
            "url": "https://github.com/EliverLara/Sweet.git"
        },
        "version": "fb691988f68737556f30c54a6df6d440b9053699"
    },
    "vscode-extension-github-copilot": {
        "cargoLocks": null,
        "date": null,
        "extract": null,
        "name": "vscode-extension-github-copilot",
        "passthru": null,
        "pinned": false,
        "src": {
            "name": "copilot-1.84.51.zip",
            "sha256": "sha256-JrVTf492G1NA4dE9qyLoScbPiA9sBqU9mKFAF97I0fA=",
            "type": "url",
            "url": "https://github.gallery.vsassets.io/_apis/public/gallery/publisher/github/extension/copilot/1.84.51/assetbyname/Microsoft.VisualStudio.Services.VSIXPackage"
        },
        "version": "1.84.51"
    },
    "vscode-extension-ms-vscode-cpptools": {
        "cargoLocks": null,
        "date": null,
        "extract": null,
        "name": "vscode-extension-ms-vscode-cpptools",
        "passthru": null,
        "pinned": false,
        "src": {
            "name": null,
            "sha256": "sha256-Fz/8zgPLq6nYnDEk9zkQp5y4uTnDJma6MbFpTJrJhGo=",
            "type": "url",
            "url": "https://github.com/microsoft/vscode-cpptools/releases/download/v1.15.4/cpptools-linux.vsix"
        },
        "version": "v1.15.4"
    }
}